pguard.py
pguard-0.4.0.dist-info/METADATA
pguard-0.4.0.dist-info/WHEEL
pguard-0.4.0.dist-info/top_level.txt
pguard-0.4.0.dist-info/RECORD
